fansi/#data.py#
fansi/__init__.py
fansi/`
fansi/data.py
fansi/emojis.json
fansi/fansi.py
fansi-0.1.7.dist-info/LICENSE
fansi-0.1.7.dist-info/WHEEL
fansi-0.1.7.dist-info/METADATA
fansi-0.1.7.dist-info/RECORD
