Metadata-Version: 2.1
Name: fansi
Version: 0.1.7
Summary: A Python library that makes formatting, colouring and adding emojis to terminal printouts easy.
Home-page: https://github.com/drivasperez/fansi/
License: UNKNOWN
Author: Daniel Rivas Perez
Author-email: drivas12@googlemail.com
Requires-Python: >=3.0,<4.0
Classifier: Programming Language :: Python :: 3
Classifier: Programming Language :: Python :: 3.4
Classifier: Programming Language :: Python :: 3.5
Classifier: Programming Language :: Python :: 3.6
Classifier: Programming Language :: Python :: 3.7
Requires-Dist: colorama (>=0.4.0,<0.5.0)
